pgstudio/__init__.py
pgstudio/manager.py
pgstudio/objects.py
pgstudio/undo_manager.py
pgstudio/utils.py
pgstudio/ui/__init__.py
pgstudio/ui/app.py
pgstudio/ui/canvas.py
pgstudio/ui/dialogs.py
pgstudio/ui/explorer.py
pgstudio/ui/properties_panel.py
pgstudio-beta/__init__.py
pgstudio-beta/manager.py
pgstudio-beta/objects.py
pgstudio-beta/undo_manager.py
pgstudio-beta/utils.py
pgstudio-beta/ui/__init__.py
pgstudio-beta/ui/app.py
pgstudio-beta/ui/canvas.py
pgstudio-beta/ui/dialogs.py
pgstudio-beta/ui/explorer.py
pgstudio-beta/ui/properties_panel.py
pgstudio-0.5.0.dist-info/METADATA
pgstudio-0.5.0.dist-info/WHEEL
pgstudio-0.5.0.dist-info/entry_points.txt
pgstudio-0.5.0.dist-info/top_level.txt
pgstudio-0.5.0.dist-info/RECORD
