Metadata-Version: 2.4
Name: pgstudio
Version: 0.5.0
Summary: A GUI builder for pygame (using pygame_gui).
Home-page: https://github.com/TaireruLLC/pgstudio
Author: Taireru LLC
Author-email: tairerullc@gmail.com
License: MIT
Classifier: Programming Language :: Python :: 3
Classifier: Operating System :: OS Independent
Requires-Python: >=3.7
Requires-Dist: pygame_gui>=0.6.0
Requires-Dist: Pillow>=9.0.0
Dynamic: author
Dynamic: author-email
Dynamic: classifier
Dynamic: description
Dynamic: description-content-type
Dynamic: home-page
Dynamic: license
Dynamic: requires-dist
Dynamic: requires-python
Dynamic: summary
